openccm/__init__.py
openccm/__main__.py
openccm/entry_points.py
openccm/run.py
openccm/compartment_models/__init__.py
openccm/compartment_models/cstr.py
openccm/compartment_models/helpers.py
openccm/compartment_models/pfr.py
openccm/compartmentalize/__init__.py
openccm/compartmentalize/unidirectional.py
openccm/config_functions/__init__.py
openccm/config_functions/expanded_config_parser.py
openccm/docs/__init__.py
openccm/docs/installation_guide.py
openccm/docs/package_interface.py
openccm/docs/pipe_recirc_OpenCMP.py
openccm/docs/pipe_recirc_OpenFOAM.py
openccm/docs/simple_reactors_cstr.py
openccm/docs/simple_reactors_pfr.py
openccm/io/__init__.py
openccm/io/opencmp.py
openccm/io/openfoam.py
openccm/mesh/__init__.py
openccm/mesh/cmesh.py
openccm/mesh/convert_ngsolve.py
openccm/mesh/convert_openfoam.py
openccm/postprocessing/__init__.py
openccm/postprocessing/analysis.py
openccm/postprocessing/vtu_output.py
openccm/system_solvers/__init__.py
openccm/system_solvers/boundary_and_initial_conditions.py
openccm/system_solvers/cstr_system.py
openccm/system_solvers/helper_functions.py
openccm/system_solvers/pfr_system.py
openccm/system_solvers/reactions.py
openccm/tests/__init__.py
openccm/tests/test_run_examples.py
openccm/tests/test_tweak_compartment_flows.py
openccm-1.0.dist-info/AUTHORS.md
openccm-1.0.dist-info/LICENSE
openccm-1.0.dist-info/METADATA
openccm-1.0.dist-info/WHEEL
openccm-1.0.dist-info/entry_points.txt
openccm-1.0.dist-info/top_level.txt
openccm-1.0.dist-info/RECORD
