Metadata-Version: 2.1
Name: openccm
Version: 1.0
Summary: OpenCCM is a compartmental modelling software package which is based on recently-developed fully automated flow alignment compartmentalization methods. It is primarily intended for large-scale flow-based processes where there is weak coupling between composition changes, e.g. through (bio)chemical reactions, and convective mass transport in the system.
License: GNU Lesser General Public License v2.1
Keywords: reduced-order modelling,compartmentalization,compartment modelling,continuum mechanics
Classifier: Topic :: Scientific/Engineering :: Physics
Classifier: License :: OSI Approved :: GNU Lesser General Public License v2 or later (LGPLv2+)
Classifier: Programming Language :: Python :: 3 :: Only
License-File: LICENSE
License-File: AUTHORS.md
Requires-Dist: numpy; python_version > "3.7.0"
Requires-Dist: scipy; python_version > "3.7.0"
Requires-Dist: sympy; python_version > "3.7.0"
Requires-Dist: numba; python_version > "3.7.0"
Requires-Dist: configparser; python_version > "3.7.0"
Requires-Dist: pyparsing; python_version > "3.7.0"
Requires-Dist: pdoc; python_version > "3.7.0"
Provides-Extra: all
Requires-Dist: pytest; python_version > "3.7" and extra == "all"
Requires-Dist: matplotlib; python_version > "3.7" and extra == "all"
Requires-Dist: networkX; python_version > "3.7" and extra == "all"
Requires-Dist: opencmp; python_version > "3.7" and extra == "all"
Provides-Extra: network_vis
Requires-Dist: matplotlib; python_version > "3.7" and extra == "network_vis"
Requires-Dist: networkX; python_version > "3.7" and extra == "network_vis"
Provides-Extra: test
Requires-Dist: pytest; python_version > "3.7" and extra == "test"
Requires-Dist: opencmp; python_version > "3.7" and extra == "test"
